vsvmafxml/__init__.py
vsvmafxml-1.0.0.dist-info/LICENSE
vsvmafxml-1.0.0.dist-info/METADATA
vsvmafxml-1.0.0.dist-info/WHEEL
vsvmafxml-1.0.0.dist-info/top_level.txt
vsvmafxml-1.0.0.dist-info/RECORD
